jref/__init__.py
jref/__main__.py
jref/context.py
jref/error.py
jref/pointer.py
jref/reference.py
jref/scalar.py
jref/uri.py
jref/version.py
jref/yaml.py
jref/test/__init__.py
jref/test/test_data.py
jref/test/test_document_cache.py
jref/test/test_pointer.py
jref/test/test_reference.py
jref/test/test_scalar.py
jref/test/test_yaml.py
jref/util/__init__.py
jref/util/document_cache_mixin.py
jref/util/equality_comparable_mixin.py
jref/util/streaming_request.py
jref-0.4.1.data/data/requirements/requirements.txt
jref-0.4.1.dist-info/LICENSE
jref-0.4.1.dist-info/METADATA
jref-0.4.1.dist-info/WHEEL
jref-0.4.1.dist-info/entry_points.txt
jref-0.4.1.dist-info/top_level.txt
jref-0.4.1.dist-info/RECORD
