Metadata-Version: 2.1
Name: jref
Version: 0.4.1
Summary: JSON Reference and JSON Pointer implementations
Home-page: https://github.com/biochimia/python-jref
Author: João Abecasis
Author-email: joao@abecasis.name
Classifier: Programming Language :: Python :: 3
Classifier: Programming Language :: Python :: 2.7
Classifier: License :: OSI Approved :: Apache Software License
Classifier: Operating System :: OS Independent
Requires-Python: >=2.7, !=3.0.*, !=3.1.*, !=3.2.*, !=3.3.*, !=3.4.*, !=3.5.*
License-File: LICENSE
Requires-Dist: pyyaml (>=6.0)
Requires-Dist: requests (==2.31.0)
